LICENSE
MANIFEST.in
README.rst
requirements-test-py26.txt
requirements-test.txt
setup.cfg
setup.py
unmatcher.py
unmatcher.egg-info/PKG-INFO
unmatcher.egg-info/SOURCES.txt
unmatcher.egg-info/dependency_links.txt
unmatcher.egg-info/top_level.txt