Metadata-Version: 1.1
Name: unmatcher
Version: 0.1.4
Summary: Regular expression reverser for Python
Home-page: https://github.com/Xion/unmatcher
Author: Karol Kuczmarski
Author-email: UNKNOWN
License: Simplified BSD
Platform: any
Classifier: Development Status :: 3 - Alpha
Classifier: Intended Audience :: Developers
Classifier: License :: OSI Approved :: BSD License
Classifier: Operating System :: OS Independent
Classifier: Programming Language :: Python
Classifier: Programming Language :: Python :: 2.7
Classifier: Programming Language :: Python :: 3.3
Classifier: Programming Language :: Python :: 3.4
Classifier: Programming Language :: Python :: Implementation :: CPython
Classifier: Programming Language :: Python :: Implementation :: PyPy
Classifier: Topic :: Software Development :: Testing
Classifier: Topic :: Text Processing :: General
